[
   {
      "domain":".colab.research.google.com",
      "expirationDate":1681433564,
      "hostOnly":false,
      "httpOnly":false,
      "name":"_ga",
      "path":"/",
      "sameSite":"unspecified",
      "secure":false,
      "session":false,
      "storeId":"0",
      "value":"GA1.4.1285781477.1618361555",
      "id":1
   },
   {
      "domain":".colab.research.google.com",
      "expirationDate":1618361615,
      "hostOnly":false,
      "httpOnly":false,
      "name":"_gat",
      "path":"/",
      "sameSite":"unspecified",
      "secure":false,
      "session":false,
      "storeId":"0",
      "value":"1",
      "id":2
   },
   {
      "domain":".colab.research.google.com",
      "expirationDate":1618447964,
      "hostOnly":false,
      "httpOnly":false,
      "name":"_gid",
      "path":"/",
      "sameSite":"unspecified",
      "secure":false,
      "session":false,
      "storeId":"0",
      "value":"GA1.4.40754673.1618361555",
      "id":3
   },
   {
      "domain":".google.com",
      "expirationDate":1681433525.804367,
      "hostOnly":false,
      "httpOnly":false,
      "name":"__Secure-3PAPISID",
      "path":"/",
      "sameSite":"no_restriction",
      "secure":true,
      "session":false,
      "storeId":"0",
      "value":"8JJyhB4wgQ20fvQI/A1bG69pR5eaBuEKiJ",
      "id":4
   },
   {
      "domain":".google.com",
      "expirationDate":1681433525.803856,
      "hostOnly":false,
      "httpOnly":true,
      "name":"__Secure-3PSID",
      "path":"/",
      "sameSite":"no_restriction",
      "secure":true,
      "session":false,
      "storeId":"0",
      "value":"8gefCz7coBuqUVvEY1uuXcepjQ01zT88JcuS1HMlGhvof9hVYe2ZJuLd9Ywo_c-h--BQyw.",
      "id":5
   },
   {
      "domain":".google.com",
      "expirationDate":1649897572.328109,
      "hostOnly":false,
      "httpOnly":true,
      "name":"__Secure-3PSIDCC",
      "path":"/",
      "sameSite":"no_restriction",
      "secure":true,
      "session":false,
      "storeId":"0",
      "value":"AJi4QfHrFBzIwOO0W0dVmmq_F2GdoEQWHWI4Us2BL9BPTe6H_fGS5Rm_AtCFINYIMuMVcyRg",
      "id":6
   },
   {
      "domain":".google.com",
      "expirationDate":1681433525.804237,
      "hostOnly":false,
      "httpOnly":false,
      "name":"APISID",
      "path":"/",
      "sameSite":"unspecified",
      "secure":false,
      "session":false,
      "storeId":"0",
      "value":"LG0bUiKiw3wmrIW9/ARkLZzioVt9eMjtsj",
      "id":7
   },
   {
      "domain":".google.com",
      "expirationDate":1681433525.80408,
      "hostOnly":false,
      "httpOnly":true,
      "name":"HSID",
      "path":"/",
      "sameSite":"unspecified",
      "secure":false,
      "session":false,
      "storeId":"0",
      "value":"AWC8vxDiQmY1_BOZ5",
      "id":8
   },
   {
      "domain":".google.com",
      "expirationDate":1634172725.804496,
      "hostOnly":false,
      "httpOnly":true,
      "name":"NID",
      "path":"/",
      "sameSite":"no_restriction",
      "secure":true,
      "session":false,
      "storeId":"0",
      "value":"213=hUaTa8vRNknD2_NCW7Lx2wslHG9-53Pp5pYbgJSDRnoUzCUP2rD8N1aoptuY9fjBBXSxtLmcUBLcKPRW7NL2B9SPp1ydsQZtHzVBXqNWX1k8UhezV3qekc7_HAX_QIQbkpHP2QZf1ldECoSmlHJaspB5ydYTnswI-JyygLS54DM",
      "id":9
   },
   {
      "domain":".google.com",
      "expirationDate":1681433525.804317,
      "hostOnly":false,
      "httpOnly":false,
      "name":"SAPISID",
      "path":"/",
      "sameSite":"unspecified",
      "secure":true,
      "session":false,
      "storeId":"0",
      "value":"8JJyhB4wgQ20fvQI/A1bG69pR5eaBuEKiJ",
      "id":10
   },
   {
      "domain":".google.com",
      "expirationDate":1681433525.803729,
      "hostOnly":false,
      "httpOnly":false,
      "name":"SID",
      "path":"/",
      "sameSite":"unspecified",
      "secure":false,
      "session":false,
      "storeId":"0",
      "value":"8gefCz7coBuqUVvEY1uuXcepjQ01zT88JcuS1HMlGhvof9hVYiLqQM3qRDG_VxmGqEjV7w.",
      "id":11
   },
   {
      "domain":".google.com",
      "expirationDate":1649897572.327998,
      "hostOnly":false,
      "httpOnly":false,
      "name":"SIDCC",
      "path":"/",
      "sameSite":"unspecified",
      "secure":false,
      "session":false,
      "storeId":"0",
      "value":"AJi4QfGDPqomnijGyodxec1bAunPA0cEj44FVrPprFsceGk2QlnUww-rq7KIuq2I6PMYGj5j",
      "id":12
   },
   {
      "domain":".google.com",
      "expirationDate":1681433525.804161,
      "hostOnly":false,
      "httpOnly":true,
      "name":"SSID",
      "path":"/",
      "sameSite":"unspecified",
      "secure":true,
      "session":false,
      "storeId":"0",
      "value":"ACxO0C__SMnLn3wOh",
      "id":13
   }
]