[
{
    "domain": ".colab.research.google.com",
    "expirationDate": 1689281148,
    "hostOnly": false,
    "httpOnly": false,
    "name": "_ga",
    "path": "/",
    "sameSite": "unspecified",
    "secure": false,
    "session": false,
    "storeId": "0",
    "value": "GA1.4.1821140828.1618341255",
    "id": 1
},
{
    "domain": ".colab.research.google.com",
    "expirationDate": 1626295548,
    "hostOnly": false,
    "httpOnly": false,
    "name": "_gid",
    "path": "/",
    "sameSite": "unspecified",
    "secure": false,
    "session": false,
    "storeId": "0",
    "value": "GA1.4.438011878.1626209130",
    "id": 2
},
{
    "domain": ".google.com",
    "expirationDate": 1689281121.637679,
    "hostOnly": false,
    "httpOnly": false,
    "name": "__Secure-3PAPISID",
    "path": "/",
    "sameSite": "no_restriction",
    "secure": true,
    "session": false,
    "storeId": "0",
    "value": "LkQ8xIvtwLmDY6sU/AESIupieI4MKUs6vK",
    "id": 3
},
{
    "domain": ".google.com",
    "expirationDate": 1689281121.637667,
    "hostOnly": false,
    "httpOnly": true,
    "name": "__Secure-3PSID",
    "path": "/",
    "sameSite": "no_restriction",
    "secure": true,
    "session": false,
    "storeId": "0",
    "value": "_weBUdmO9d2i4J0Ejn7KSz0xXIHZN8eoVcALFfU_WNLulFurcZgZRaDx4DM1j1DIscU7Pw.",
    "id": 4
},
{
    "domain": ".google.com",
    "expirationDate": 1657745303.079062,
    "hostOnly": false,
    "httpOnly": true,
    "name": "__Secure-3PSIDCC",
    "path": "/",
    "sameSite": "no_restriction",
    "secure": true,
    "session": false,
    "storeId": "0",
    "value": "AJi4QfFanjzoI65bAsDN6D0Sqdap5-gH0Kk9q6Xp_VGUD_kdSYOGb_zL2wtV2geEks-yBEzZIw",
    "id": 5
},
{
    "domain": ".google.com",
    "expirationDate": 1689281121.637676,
    "hostOnly": false,
    "httpOnly": false,
    "name": "APISID",
    "path": "/",
    "sameSite": "unspecified",
    "secure": false,
    "session": false,
    "storeId": "0",
    "value": "cLNeUAomNfo43xHC/AhhMQZ9QWa5R80IYn",
    "id": 6
},
{
    "domain": ".google.com",
    "expirationDate": 1689281121.637673,
    "hostOnly": false,
    "httpOnly": true,
    "name": "HSID",
    "path": "/",
    "sameSite": "unspecified",
    "secure": false,
    "session": false,
    "storeId": "0",
    "value": "A11ESDb6p_FiyMvZr",
    "id": 7
},
{
    "domain": ".google.com",
    "expirationDate": 1637345987.711514,
    "hostOnly": false,
    "httpOnly": true,
    "name": "NID",
    "path": "/",
    "sameSite": "no_restriction",
    "secure": true,
    "session": false,
    "storeId": "0",
    "value": "216=L7Ivwe1D4Ew7aCB_X5b1xyPS_j5SIRMdK105rZ_QhZS8ZOp5qV6l1-BIOSldEVDsd9mpHP8WO3HOThGipSd--cPXAI9dFK1UN465b5yRmQjS12gGh7tkOfyTq5oDGjXW4RbtqT7AP6lN9N0FKSIRln6NQaVUivplUPO_4DCi5Kw",
    "id": 8
},
{
    "domain": ".google.com",
    "expirationDate": 1689281121.637677,
    "hostOnly": false,
    "httpOnly": false,
    "name": "SAPISID",
    "path": "/",
    "sameSite": "unspecified",
    "secure": true,
    "session": false,
    "storeId": "0",
    "value": "LkQ8xIvtwLmDY6sU/AESIupieI4MKUs6vK",
    "id": 9
},
{
    "domain": ".google.com",
    "expirationDate": 1689281121.637661,
    "hostOnly": false,
    "httpOnly": false,
    "name": "SID",
    "path": "/",
    "sameSite": "unspecified",
    "secure": false,
    "session": false,
    "storeId": "0",
    "value": "_weBUdmO9d2i4J0Ejn7KSz0xXIHZN8eoVcALFfU_WNLulFur7AOeoiDJ0OQcwwR4W-kCwA.",
    "id": 10
},
{
    "domain": ".google.com",
    "expirationDate": 1657745303.078931,
    "hostOnly": false,
    "httpOnly": false,
    "name": "SIDCC",
    "path": "/",
    "sameSite": "unspecified",
    "secure": false,
    "session": false,
    "storeId": "0",
    "value": "AJi4QfHmszBn1CefDHDokWNWoh9MWIi-e_bENAuyyBjuxopZWN9tIxYn9eu95VyHU3XGpIJTU5Q",
    "id": 11
},
{
    "domain": ".google.com",
    "expirationDate": 1689281121.637675,
    "hostOnly": false,
    "httpOnly": true,
    "name": "SSID",
    "path": "/",
    "sameSite": "unspecified",
    "secure": true,
    "session": false,
    "storeId": "0",
    "value": "AdcRcrb7E1W4KTIni",
    "id": 12
}
]