[
{
    "domain": ".colab.research.google.com",
    "expirationDate": 1689281542,
    "hostOnly": false,
    "httpOnly": false,
    "name": "_ga",
    "path": "/",
    "sameSite": "unspecified",
    "secure": false,
    "session": false,
    "storeId": "0",
    "value": "GA1.4.411519952.1618362745",
    "id": 1
},
{
    "domain": ".colab.research.google.com",
    "expirationDate": 1626209555,
    "hostOnly": false,
    "httpOnly": false,
    "name": "_gat",
    "path": "/",
    "sameSite": "unspecified",
    "secure": false,
    "session": false,
    "storeId": "0",
    "value": "1",
    "id": 2
},
{
    "domain": ".colab.research.google.com",
    "expirationDate": 1626295942,
    "hostOnly": false,
    "httpOnly": false,
    "name": "_gid",
    "path": "/",
    "sameSite": "unspecified",
    "secure": false,
    "session": false,
    "storeId": "0",
    "value": "GA1.4.2095842694.1626209495",
    "id": 3
},
{
    "domain": ".google.com",
    "expirationDate": 1689281487.264053,
    "hostOnly": false,
    "httpOnly": false,
    "name": "__Secure-3PAPISID",
    "path": "/",
    "sameSite": "no_restriction",
    "secure": true,
    "session": false,
    "storeId": "0",
    "value": "BZm2isXSVqOzw-U_/AYUXjiLcFvO7Scbyw",
    "id": 4
},
{
    "domain": ".google.com",
    "expirationDate": 1689281487.26404,
    "hostOnly": false,
    "httpOnly": true,
    "name": "__Secure-3PSID",
    "path": "/",
    "sameSite": "no_restriction",
    "secure": true,
    "session": false,
    "storeId": "0",
    "value": "_wchoKiXXOE2jysFfo30l1t7ABpxnxEf_2V6xn-SF-vwd0Pcal1F7U7c_6rR2KlcDtDwIQ.",
    "id": 5
},
{
    "domain": ".google.com",
    "expirationDate": 1657745549.982546,
    "hostOnly": false,
    "httpOnly": true,
    "name": "__Secure-3PSIDCC",
    "path": "/",
    "sameSite": "no_restriction",
    "secure": true,
    "session": false,
    "storeId": "0",
    "value": "AJi4QfF1kZTHxghE-kw1k2QqkUcpkVNKYNuxDymPYwtOOS4G0g6b0e35e4YrR8r8mNv-wqzxOxc",
    "id": 6
},
{
    "domain": ".google.com",
    "expirationDate": 1689281487.26405,
    "hostOnly": false,
    "httpOnly": false,
    "name": "APISID",
    "path": "/",
    "sameSite": "unspecified",
    "secure": false,
    "session": false,
    "storeId": "0",
    "value": "mABwmWHP3-nvlK0Z/AIPEzukJGgjU-3oAf",
    "id": 7
},
{
    "domain": ".google.com",
    "expirationDate": 1689281487.264047,
    "hostOnly": false,
    "httpOnly": true,
    "name": "HSID",
    "path": "/",
    "sameSite": "unspecified",
    "secure": false,
    "session": false,
    "storeId": "0",
    "value": "AzZr4rz-y4dPwpRcv",
    "id": 8
},
{
    "domain": ".google.com",
    "expirationDate": 1642020740.399447,
    "hostOnly": false,
    "httpOnly": true,
    "name": "NID",
    "path": "/",
    "sameSite": "no_restriction",
    "secure": true,
    "session": false,
    "storeId": "0",
    "value": "219=pIGRHWXWyNNAnXQIUbhfgLxeMyK1_kN78jwxIsIxaIXqqtQP42R5Z9FclXZqeBMg-FS5V9SSkiACAEUA3vpa0M1X-bRROdTQ3G_ek8GN9WZ-bwXfZrHeEle5jIxzdnVH3m_8zin2hlRve3jetYJJqiil5778o_BmzBCW0xNthX4",
    "id": 9
},
{
    "domain": ".google.com",
    "expirationDate": 1689281487.264051,
    "hostOnly": false,
    "httpOnly": false,
    "name": "SAPISID",
    "path": "/",
    "sameSite": "unspecified",
    "secure": true,
    "session": false,
    "storeId": "0",
    "value": "BZm2isXSVqOzw-U_/AYUXjiLcFvO7Scbyw",
    "id": 10
},
{
    "domain": ".google.com",
    "expirationDate": 1689281487.264036,
    "hostOnly": false,
    "httpOnly": false,
    "name": "SID",
    "path": "/",
    "sameSite": "unspecified",
    "secure": false,
    "session": false,
    "storeId": "0",
    "value": "_wchoKiXXOE2jysFfo30l1t7ABpxnxEf_2V6xn-SF-vwd0PcfY5BfjJrd2hD5lfloWptfA.",
    "id": 11
},
{
    "domain": ".google.com",
    "expirationDate": 1657745549.98245,
    "hostOnly": false,
    "httpOnly": false,
    "name": "SIDCC",
    "path": "/",
    "sameSite": "unspecified",
    "secure": false,
    "session": false,
    "storeId": "0",
    "value": "AJi4QfHt2wqT7BQWMFG5RCBSDb8-HNLhiaCdlpmhj2ADS_Ovx0zUvkCsAk31sTNjaCVS_u5aVvc",
    "id": 12
},
{
    "domain": ".google.com",
    "expirationDate": 1689281487.264048,
    "hostOnly": false,
    "httpOnly": true,
    "name": "SSID",
    "path": "/",
    "sameSite": "unspecified",
    "secure": true,
    "session": false,
    "storeId": "0",
    "value": "AHUb9jFR3rZXcTIKa",
    "id": 13
}
]